odoo8_addon_report_qweb_signer-8.0.1.0.0.99.dev30-py3.8-nspkg.pth
odoo_addons/report_qweb_signer/README.rst
odoo_addons/report_qweb_signer/__init__.py
odoo_addons/report_qweb_signer/__openerp__.py
odoo_addons/report_qweb_signer/demo/report_certificate.xml
odoo_addons/report_qweb_signer/demo/report_partner.xml
odoo_addons/report_qweb_signer/i18n/am.po
odoo_addons/report_qweb_signer/i18n/ar.po
odoo_addons/report_qweb_signer/i18n/bg.po
odoo_addons/report_qweb_signer/i18n/bs.po
odoo_addons/report_qweb_signer/i18n/ca.po
odoo_addons/report_qweb_signer/i18n/ca_ES.po
odoo_addons/report_qweb_signer/i18n/cs.po
odoo_addons/report_qweb_signer/i18n/da.po
odoo_addons/report_qweb_signer/i18n/da_DK.po
odoo_addons/report_qweb_signer/i18n/de.po
odoo_addons/report_qweb_signer/i18n/el_GR.po
odoo_addons/report_qweb_signer/i18n/en_GB.po
odoo_addons/report_qweb_signer/i18n/es.po
odoo_addons/report_qweb_signer/i18n/es_AR.po
odoo_addons/report_qweb_signer/i18n/es_CL.po
odoo_addons/report_qweb_signer/i18n/es_CO.po
odoo_addons/report_qweb_signer/i18n/es_CR.po
odoo_addons/report_qweb_signer/i18n/es_DO.po
odoo_addons/report_qweb_signer/i18n/es_EC.po
odoo_addons/report_qweb_signer/i18n/es_ES.po
odoo_addons/report_qweb_signer/i18n/es_MX.po
odoo_addons/report_qweb_signer/i18n/es_PE.po
odoo_addons/report_qweb_signer/i18n/es_PY.po
odoo_addons/report_qweb_signer/i18n/es_VE.po
odoo_addons/report_qweb_signer/i18n/et.po
odoo_addons/report_qweb_signer/i18n/eu.po
odoo_addons/report_qweb_signer/i18n/fa.po
odoo_addons/report_qweb_signer/i18n/fi.po
odoo_addons/report_qweb_signer/i18n/fr.po
odoo_addons/report_qweb_signer/i18n/fr_CA.po
odoo_addons/report_qweb_signer/i18n/fr_CH.po
odoo_addons/report_qweb_signer/i18n/fr_FR.po
odoo_addons/report_qweb_signer/i18n/gl.po
odoo_addons/report_qweb_signer/i18n/gl_ES.po
odoo_addons/report_qweb_signer/i18n/he.po
odoo_addons/report_qweb_signer/i18n/hr.po
odoo_addons/report_qweb_signer/i18n/hr_HR.po
odoo_addons/report_qweb_signer/i18n/hu.po
odoo8_addon_report_qweb_signer-8.0.1.0.0.99.dev30.dist-info/METADATA
odoo8_addon_report_qweb_signer-8.0.1.0.0.99.dev30.dist-info/WHEEL
odoo8_addon_report_qweb_signer-8.0.1.0.0.99.dev30.dist-info/namespace_packages.txt
odoo8_addon_report_qweb_signer-8.0.1.0.0.99.dev30.dist-info/top_level.txt
odoo8_addon_report_qweb_signer-8.0.1.0.0.99.dev30.dist-info/RECORD
